{
    "$schema": "https://raw.githubusercontent.com/crossbario/crossbar/master/crossbar.json",
    "version": 2,
    "controller": {
        "id": "lojack1",
        "enable_docker": false,
        "fabric": {
        }
    },
    "workers": [
        {
            "id": "rtr1",
            "type": "router",
            "realms": [

                {
                    "name": "dvl1",
                    "roles": [
                        {
                            "name": "anonymous",
                            "permissions": [
                                {
                                    "uri": "",
                                    "match": "prefix",
                                    "allow": {
                                        "call": true,
                                        "register": true,
                                        "publish": true,
                                        "subscribe": true
                                    },
                                    "disclose": {
                                        "caller": true,
                                        "publisher": true
                                    },
                                    "cache": true
                                }
                            ]
                        }
                    ]
                },

                {
                    "name": "dvl2",
                    "roles": [
                        {
                            "name": "anonymous",
                            "permissions": [
                                {
                                    "uri": "",
                                    "match": "prefix",
                                    "allow": {
                                        "call": true,
                                        "register": true,
                                        "publish": true,
                                        "subscribe": true
                                    },
                                    "disclose": {
                                        "caller": true,
                                        "publisher": true
                                    },
                                    "cache": true
                                }
                            ]
                        }
                    ]
                },

                {
                    "name": "dvl3",
                    "roles": [
                        {
                            "name": "anonymous",
                            "permissions": [
                                {
                                    "uri": "",
                                    "match": "prefix",
                                    "allow": {
                                        "call": true,
                                        "register": true,
                                        "publish": true,
                                        "subscribe": true
                                    },
                                    "disclose": {
                                        "caller": true,
                                        "publisher": true
                                    },
                                    "cache": true
                                }
                            ]
                        }
                    ]
                },

                {
                    "name": "dvl4",
                    "roles": [
                        {
                            "name": "anonymous",
                            "permissions": [
                                {
                                    "uri": "",
                                    "match": "prefix",
                                    "allow": {
                                        "call": true,
                                        "register": true,
                                        "publish": true,
                                        "subscribe": true
                                    },
                                    "disclose": {
                                        "caller": true,
                                        "publisher": true
                                    },
                                    "cache": true
                                }
                            ]
                        }
                    ]
                },

                {
                    "name": "dvl5",
                    "roles": [
                        {
                            "name": "anonymous",
                            "permissions": [
                                {
                                    "uri": "",
                                    "match": "prefix",
                                    "allow": {
                                        "call": true,
                                        "register": true,
                                        "publish": true,
                                        "subscribe": true
                                    },
                                    "disclose": {
                                        "caller": true,
                                        "publisher": true
                                    },
                                    "cache": true
                                }
                            ]
                        }
                    ]
                },

                {
                    "name": "dvl6",
                    "roles": [
                        {
                            "name": "anonymous",
                            "permissions": [
                                {
                                    "uri": "",
                                    "match": "prefix",
                                    "allow": {
                                        "call": true,
                                        "register": true,
                                        "publish": true,
                                        "subscribe": true
                                    },
                                    "disclose": {
                                        "caller": true,
                                        "publisher": true
                                    },
                                    "cache": true
                                }
                            ]
                        }
                    ]
                },

                {
                    "name": "dvl7",
                    "roles": [
                        {
                            "name": "anonymous",
                            "permissions": [
                                {
                                    "uri": "",
                                    "match": "prefix",
                                    "allow": {
                                        "call": true,
                                        "register": true,
                                        "publish": true,
                                        "subscribe": true
                                    },
                                    "disclose": {
                                        "caller": true,
                                        "publisher": true
                                    },
                                    "cache": true
                                }
                            ]
                        }
                    ]
                },

                {
                    "name": "dvl8",
                    "roles": [
                        {
                            "name": "anonymous",
                            "permissions": [
                                {
                                    "uri": "",
                                    "match": "prefix",
                                    "allow": {
                                        "call": true,
                                        "register": true,
                                        "publish": true,
                                        "subscribe": true
                                    },
                                    "disclose": {
                                        "caller": true,
                                        "publisher": true
                                    },
                                    "cache": true
                                }
                            ]
                        }
                    ]
                },

                {
                    "name": "dvl9",
                    "roles": [
                        {
                            "name": "anonymous",
                            "permissions": [
                                {
                                    "uri": "",
                                    "match": "prefix",
                                    "allow": {
                                        "call": true,
                                        "register": true,
                                        "publish": true,
                                        "subscribe": true
                                    },
                                    "disclose": {
                                        "caller": true,
                                        "publisher": true
                                    },
                                    "cache": true
                                }
                            ]
                        }
                    ]
                },

                {
                    "name": "dvl10",
                    "roles": [
                        {
                            "name": "anonymous",
                            "permissions": [
                                {
                                    "uri": "",
                                    "match": "prefix",
                                    "allow": {
                                        "call": true,
                                        "register": true,
                                        "publish": true,
                                        "subscribe": true
                                    },
                                    "disclose": {
                                        "caller": true,
                                        "publisher": true
                                    },
                                    "cache": true
                                }
                            ]
                        }
                    ]
                }
                
            ],
            "transports": [
                {
                    "type": "rawsocket",
                    "endpoint": {
                        "type": "unix",
                        "path": "rtr1.sock"
                    },
                    "options": {
                        "max_message_size": 1048576
                    },
                    "serializers": ["cbor"],
                    "auth": {
                        "anonymous": {
                            "type": "static",
                            "role": "anonymous"
                        }
                    }
                }
            ]
        },

        {
            "id": "pxy0",
            "type": "proxy",
            "options": {
            },
            "transports": [
                {
                    "type": "rawsocket",
                    "endpoint": {
                        "type": "tcp",
                        "port": 8080,
                        "shared": true,
                        "backlog": 1024
                    },
                    "serializers": [
                        "cbor", "msgpack", "json"
                    ],
                    "backends": [
                        {
                            "type": "rawsocket",
                            "endpoint": {
                                "type": "unix",
                                "path": "rtr1.sock"
                            },
                            "url": "ws://localhost",
                            "serializer": "cbor"
                        }
                    ],
                    "options": {
                        "max_message_size": 1048576
                    },
                    "auth": {
                        "anonymous": {
                            "type": "static",
                            "role": "anonymous"
                        }
                    }
                },
                {
                    "type": "websocket",
                    "endpoint": {
                        "type": "tcp",
                        "port": 80,
                        "shared": true,
                        "backlog": 1024
                    },
                    "serializers": [
                        "cbor", "msgpack", "json"
                    ],
                    "backends": [
                        {
                            "type": "rawsocket",
                            "endpoint": {
                                "type": "unix",
                                "path": "rtr1.sock"
                            },
                            "url": "ws://localhost",
                            "serializer": "cbor"
                        }
                    ],
                    "options": {
                        "allowed_origins": ["*"],
                        "allow_null_origin": true,
                        "enable_webstatus": true,
                        "max_frame_size": 1048576,
                        "max_message_size": 1048576,
                        "auto_fragment_size": 65536,
                        "fail_by_drop": true,
                        "open_handshake_timeout": 2500,
                        "close_handshake_timeout": 1000,
                        "auto_ping_interval": 10000,
                        "auto_ping_timeout": 5000,
                        "auto_ping_size": 4,
                        "compression": {
                            "deflate": {
                                "request_no_context_takeover": false,
                                "request_max_window_bits": 13,
                                "no_context_takeover": false,
                                "max_window_bits": 13,
                                "memory_level": 5
                            }
                        }
                    },
                    "auth": {
                        "anonymous": {
                            "type": "static",
                            "role": "anonymous"
                        }
                    }
                },
                {
                    "type": "rawsocket",
                    "endpoint": {
                        "type": "tcp",
                        "port": 8443,
                        "shared": true,
                        "backlog": 1024,
                        "tls": {
                            "certificate": "lojack1.crossbario.com.crt",
                            "key": "lojack1.crossbario.com.key",
                            "dhparam": "dhparam.pem",
                            "chain_certificates": [
                                "lojack1.crossbario.com.issuer.crt"
                            ],
                            "ciphers": "ECDHE-RSA-AES256-GCM-SHA384:ECDHE-RSA-AES128-GCM-SHA256:DHE-RSA-AES256-GCM-SHA384:DHE-RSA-AES128-GCM-SHA256:ECDHE-RSA-AES256-SHA384:ECDHE-RSA-AES128-SHA256:DHE-RSA-AES256-SHA256:DHE-RSA-AES128-SHA256"
                        }
                    },
                    "serializers": [
                        "cbor", "msgpack", "json"
                    ],
                    "backends": [
                        {
                            "type": "rawsocket",
                            "endpoint": {
                                "type": "unix",
                                "path": "rtr1.sock"
                            },
                            "url": "ws://localhost",
                            "serializer": "cbor"
                        }
                    ],
                    "options": {
                        "max_message_size": 1048576
                    },
                    "auth": {
                        "anonymous": {
                            "type": "static",
                            "role": "anonymous"
                        }
                    }
                },
                {
                    "type": "websocket",
                    "endpoint": {
                        "type": "tcp",
                        "port": 443,
                        "shared": true,
                        "backlog": 1024,
                        "tls": {
                            "certificate": "lojack1.crossbario.com.crt",
                            "key": "lojack1.crossbario.com.key",
                            "dhparam": "dhparam.pem",
                            "chain_certificates": [
                                "lojack1.crossbario.com.issuer.crt"
                            ],
                            "ciphers": "ECDHE-RSA-AES256-GCM-SHA384:ECDHE-RSA-AES128-GCM-SHA256:DHE-RSA-AES256-GCM-SHA384:DHE-RSA-AES128-GCM-SHA256:ECDHE-RSA-AES256-SHA384:ECDHE-RSA-AES128-SHA256:DHE-RSA-AES256-SHA256:DHE-RSA-AES128-SHA256"
                        }
                    },
                    "serializers": [
                        "cbor", "msgpack", "json"
                    ],
                    "backends": [
                        {
                            "type": "rawsocket",
                            "endpoint": {
                                "type": "unix",
                                "path": "rtr1.sock"
                            },
                            "url": "ws://localhost",
                            "serializer": "cbor"
                        }
                    ],
                    "options": {
                        "allowed_origins": ["*"],
                        "allow_null_origin": true,
                        "enable_webstatus": true,
                        "max_frame_size": 1048576,
                        "max_message_size": 1048576,
                        "auto_fragment_size": 65536,
                        "fail_by_drop": true,
                        "open_handshake_timeout": 2500,
                        "close_handshake_timeout": 1000,
                        "auto_ping_interval": 10000,
                        "auto_ping_timeout": 5000,
                        "auto_ping_size": 4,
                        "compression": {
                            "deflate": {
                                "request_no_context_takeover": false,
                                "request_max_window_bits": 13,
                                "no_context_takeover": false,
                                "max_window_bits": 13,
                                "memory_level": 5
                            }
                        }
                    },
                    "auth": {
                        "anonymous": {
                            "type": "static",
                            "role": "anonymous"
                        }
                    }
                }
            ]
        },

        {
            "id": "pxy1",
            "type": "proxy",
            "options": {
            },
            "transports": [
                {
                    "type": "rawsocket",
                    "endpoint": {
                        "type": "tcp",
                        "port": 8080,
                        "shared": true,
                        "backlog": 1024
                    },
                    "serializers": [
                        "cbor", "msgpack", "json"
                    ],
                    "backends": [
                        {
                            "type": "rawsocket",
                            "endpoint": {
                                "type": "unix",
                                "path": "rtr1.sock"
                            },
                            "url": "ws://localhost",
                            "serializer": "cbor"
                        }
                    ],
                    "options": {
                        "max_message_size": 1048576
                    },
                    "auth": {
                        "anonymous": {
                            "type": "static",
                            "role": "anonymous"
                        }
                    }
                },
                {
                    "type": "websocket",
                    "endpoint": {
                        "type": "tcp",
                        "port": 80,
                        "shared": true,
                        "backlog": 1024
                    },
                    "serializers": [
                        "cbor", "msgpack", "json"
                    ],
                    "backends": [
                        {
                            "type": "rawsocket",
                            "endpoint": {
                                "type": "unix",
                                "path": "rtr1.sock"
                            },
                            "url": "ws://localhost",
                            "serializer": "cbor"
                        }
                    ],
                    "options": {
                        "allowed_origins": ["*"],
                        "allow_null_origin": true,
                        "enable_webstatus": true,
                        "max_frame_size": 1048576,
                        "max_message_size": 1048576,
                        "auto_fragment_size": 65536,
                        "fail_by_drop": true,
                        "open_handshake_timeout": 2500,
                        "close_handshake_timeout": 1000,
                        "auto_ping_interval": 10000,
                        "auto_ping_timeout": 5000,
                        "auto_ping_size": 4,
                        "compression": {
                            "deflate": {
                                "request_no_context_takeover": false,
                                "request_max_window_bits": 13,
                                "no_context_takeover": false,
                                "max_window_bits": 13,
                                "memory_level": 5
                            }
                        }
                    },
                    "auth": {
                        "anonymous": {
                            "type": "static",
                            "role": "anonymous"
                        }
                    }
                },
                {
                    "type": "rawsocket",
                    "endpoint": {
                        "type": "tcp",
                        "port": 8443,
                        "shared": true,
                        "backlog": 1024,
                        "tls": {
                            "certificate": "lojack1.crossbario.com.crt",
                            "key": "lojack1.crossbario.com.key",
                            "dhparam": "dhparam.pem",
                            "chain_certificates": [
                                "lojack1.crossbario.com.issuer.crt"
                            ],
                            "ciphers": "ECDHE-RSA-AES256-GCM-SHA384:ECDHE-RSA-AES128-GCM-SHA256:DHE-RSA-AES256-GCM-SHA384:DHE-RSA-AES128-GCM-SHA256:ECDHE-RSA-AES256-SHA384:ECDHE-RSA-AES128-SHA256:DHE-RSA-AES256-SHA256:DHE-RSA-AES128-SHA256"
                        }
                    },
                    "serializers": [
                        "cbor", "msgpack", "json"
                    ],
                    "backends": [
                        {
                            "type": "rawsocket",
                            "endpoint": {
                                "type": "unix",
                                "path": "rtr1.sock"
                            },
                            "url": "ws://localhost",
                            "serializer": "cbor"
                        }
                    ],
                    "options": {
                        "max_message_size": 1048576
                    },
                    "auth": {
                        "anonymous": {
                            "type": "static",
                            "role": "anonymous"
                        }
                    }
                },
                {
                    "type": "websocket",
                    "endpoint": {
                        "type": "tcp",
                        "port": 443,
                        "shared": true,
                        "backlog": 1024,
                        "tls": {
                            "certificate": "lojack1.crossbario.com.crt",
                            "key": "lojack1.crossbario.com.key",
                            "dhparam": "dhparam.pem",
                            "chain_certificates": [
                                "lojack1.crossbario.com.issuer.crt"
                            ],
                            "ciphers": "ECDHE-RSA-AES256-GCM-SHA384:ECDHE-RSA-AES128-GCM-SHA256:DHE-RSA-AES256-GCM-SHA384:DHE-RSA-AES128-GCM-SHA256:ECDHE-RSA-AES256-SHA384:ECDHE-RSA-AES128-SHA256:DHE-RSA-AES256-SHA256:DHE-RSA-AES128-SHA256"
                        }
                    },
                    "serializers": [
                        "cbor", "msgpack", "json"
                    ],
                    "backends": [
                        {
                            "type": "rawsocket",
                            "endpoint": {
                                "type": "unix",
                                "path": "rtr1.sock"
                            },
                            "url": "ws://localhost",
                            "serializer": "cbor"
                        }
                    ],
                    "options": {
                        "allowed_origins": ["*"],
                        "allow_null_origin": true,
                        "enable_webstatus": true,
                        "max_frame_size": 1048576,
                        "max_message_size": 1048576,
                        "auto_fragment_size": 65536,
                        "fail_by_drop": true,
                        "open_handshake_timeout": 2500,
                        "close_handshake_timeout": 1000,
                        "auto_ping_interval": 10000,
                        "auto_ping_timeout": 5000,
                        "auto_ping_size": 4,
                        "compression": {
                            "deflate": {
                                "request_no_context_takeover": false,
                                "request_max_window_bits": 13,
                                "no_context_takeover": false,
                                "max_window_bits": 13,
                                "memory_level": 5
                            }
                        }
                    },
                    "auth": {
                        "anonymous": {
                            "type": "static",
                            "role": "anonymous"
                        }
                    }
                }
            ]
        },

        {
            "id": "pxy2",
            "type": "proxy",
            "options": {
            },
            "transports": [
                {
                    "type": "rawsocket",
                    "endpoint": {
                        "type": "tcp",
                        "port": 8080,
                        "shared": true,
                        "backlog": 1024
                    },
                    "serializers": [
                        "cbor", "msgpack", "json"
                    ],
                    "backends": [
                        {
                            "type": "rawsocket",
                            "endpoint": {
                                "type": "unix",
                                "path": "rtr1.sock"
                            },
                            "url": "ws://localhost",
                            "serializer": "cbor"
                        }
                    ],
                    "options": {
                        "max_message_size": 1048576
                    },
                    "auth": {
                        "anonymous": {
                            "type": "static",
                            "role": "anonymous"
                        }
                    }
                },
                {
                    "type": "websocket",
                    "endpoint": {
                        "type": "tcp",
                        "port": 80,
                        "shared": true,
                        "backlog": 1024
                    },
                    "serializers": [
                        "cbor", "msgpack", "json"
                    ],
                    "backends": [
                        {
                            "type": "rawsocket",
                            "endpoint": {
                                "type": "unix",
                                "path": "rtr1.sock"
                            },
                            "url": "ws://localhost",
                            "serializer": "cbor"
                        }
                    ],
                    "options": {
                        "allowed_origins": ["*"],
                        "allow_null_origin": true,
                        "enable_webstatus": true,
                        "max_frame_size": 1048576,
                        "max_message_size": 1048576,
                        "auto_fragment_size": 65536,
                        "fail_by_drop": true,
                        "open_handshake_timeout": 2500,
                        "close_handshake_timeout": 1000,
                        "auto_ping_interval": 10000,
                        "auto_ping_timeout": 5000,
                        "auto_ping_size": 4,
                        "compression": {
                            "deflate": {
                                "request_no_context_takeover": false,
                                "request_max_window_bits": 13,
                                "no_context_takeover": false,
                                "max_window_bits": 13,
                                "memory_level": 5
                            }
                        }
                    },
                    "auth": {
                        "anonymous": {
                            "type": "static",
                            "role": "anonymous"
                        }
                    }
                },
                {
                    "type": "rawsocket",
                    "endpoint": {
                        "type": "tcp",
                        "port": 8443,
                        "shared": true,
                        "backlog": 1024,
                        "tls": {
                            "certificate": "lojack1.crossbario.com.crt",
                            "key": "lojack1.crossbario.com.key",
                            "dhparam": "dhparam.pem",
                            "chain_certificates": [
                                "lojack1.crossbario.com.issuer.crt"
                            ],
                            "ciphers": "ECDHE-RSA-AES256-GCM-SHA384:ECDHE-RSA-AES128-GCM-SHA256:DHE-RSA-AES256-GCM-SHA384:DHE-RSA-AES128-GCM-SHA256:ECDHE-RSA-AES256-SHA384:ECDHE-RSA-AES128-SHA256:DHE-RSA-AES256-SHA256:DHE-RSA-AES128-SHA256"
                        }
                    },
                    "serializers": [
                        "cbor", "msgpack", "json"
                    ],
                    "backends": [
                        {
                            "type": "rawsocket",
                            "endpoint": {
                                "type": "unix",
                                "path": "rtr1.sock"
                            },
                            "url": "ws://localhost",
                            "serializer": "cbor"
                        }
                    ],
                    "options": {
                        "max_message_size": 1048576
                    },
                    "auth": {
                        "anonymous": {
                            "type": "static",
                            "role": "anonymous"
                        }
                    }
                },
                {
                    "type": "websocket",
                    "endpoint": {
                        "type": "tcp",
                        "port": 443,
                        "shared": true,
                        "backlog": 1024,
                        "tls": {
                            "certificate": "lojack1.crossbario.com.crt",
                            "key": "lojack1.crossbario.com.key",
                            "dhparam": "dhparam.pem",
                            "chain_certificates": [
                                "lojack1.crossbario.com.issuer.crt"
                            ],
                            "ciphers": "ECDHE-RSA-AES256-GCM-SHA384:ECDHE-RSA-AES128-GCM-SHA256:DHE-RSA-AES256-GCM-SHA384:DHE-RSA-AES128-GCM-SHA256:ECDHE-RSA-AES256-SHA384:ECDHE-RSA-AES128-SHA256:DHE-RSA-AES256-SHA256:DHE-RSA-AES128-SHA256"
                        }
                    },
                    "serializers": [
                        "cbor", "msgpack", "json"
                    ],
                    "backends": [
                        {
                            "type": "rawsocket",
                            "endpoint": {
                                "type": "unix",
                                "path": "rtr1.sock"
                            },
                            "url": "ws://localhost",
                            "serializer": "cbor"
                        }
                    ],
                    "options": {
                        "allowed_origins": ["*"],
                        "allow_null_origin": true,
                        "enable_webstatus": true,
                        "max_frame_size": 1048576,
                        "max_message_size": 1048576,
                        "auto_fragment_size": 65536,
                        "fail_by_drop": true,
                        "open_handshake_timeout": 2500,
                        "close_handshake_timeout": 1000,
                        "auto_ping_interval": 10000,
                        "auto_ping_timeout": 5000,
                        "auto_ping_size": 4,
                        "compression": {
                            "deflate": {
                                "request_no_context_takeover": false,
                                "request_max_window_bits": 13,
                                "no_context_takeover": false,
                                "max_window_bits": 13,
                                "memory_level": 5
                            }
                        }
                    },
                    "auth": {
                        "anonymous": {
                            "type": "static",
                            "role": "anonymous"
                        }
                    }
                }
            ]
        },

        {
            "id": "pxy3",
            "type": "proxy",
            "options": {
            },
            "transports": [
                {
                    "type": "rawsocket",
                    "endpoint": {
                        "type": "tcp",
                        "port": 8080,
                        "shared": true,
                        "backlog": 1024
                    },
                    "serializers": [
                        "cbor", "msgpack", "json"
                    ],
                    "backends": [
                        {
                            "type": "rawsocket",
                            "endpoint": {
                                "type": "unix",
                                "path": "rtr1.sock"
                            },
                            "url": "ws://localhost",
                            "serializer": "cbor"
                        }
                    ],
                    "options": {
                        "max_message_size": 1048576
                    },
                    "auth": {
                        "anonymous": {
                            "type": "static",
                            "role": "anonymous"
                        }
                    }
                },
                {
                    "type": "websocket",
                    "endpoint": {
                        "type": "tcp",
                        "port": 80,
                        "shared": true,
                        "backlog": 1024
                    },
                    "serializers": [
                        "cbor", "msgpack", "json"
                    ],
                    "backends": [
                        {
                            "type": "rawsocket",
                            "endpoint": {
                                "type": "unix",
                                "path": "rtr1.sock"
                            },
                            "url": "ws://localhost",
                            "serializer": "cbor"
                        }
                    ],
                    "options": {
                        "allowed_origins": ["*"],
                        "allow_null_origin": true,
                        "enable_webstatus": true,
                        "max_frame_size": 1048576,
                        "max_message_size": 1048576,
                        "auto_fragment_size": 65536,
                        "fail_by_drop": true,
                        "open_handshake_timeout": 2500,
                        "close_handshake_timeout": 1000,
                        "auto_ping_interval": 10000,
                        "auto_ping_timeout": 5000,
                        "auto_ping_size": 4,
                        "compression": {
                            "deflate": {
                                "request_no_context_takeover": false,
                                "request_max_window_bits": 13,
                                "no_context_takeover": false,
                                "max_window_bits": 13,
                                "memory_level": 5
                            }
                        }
                    },
                    "auth": {
                        "anonymous": {
                            "type": "static",
                            "role": "anonymous"
                        }
                    }
                },
                {
                    "type": "rawsocket",
                    "endpoint": {
                        "type": "tcp",
                        "port": 8443,
                        "shared": true,
                        "backlog": 1024,
                        "tls": {
                            "certificate": "lojack1.crossbario.com.crt",
                            "key": "lojack1.crossbario.com.key",
                            "dhparam": "dhparam.pem",
                            "chain_certificates": [
                                "lojack1.crossbario.com.issuer.crt"
                            ],
                            "ciphers": "ECDHE-RSA-AES256-GCM-SHA384:ECDHE-RSA-AES128-GCM-SHA256:DHE-RSA-AES256-GCM-SHA384:DHE-RSA-AES128-GCM-SHA256:ECDHE-RSA-AES256-SHA384:ECDHE-RSA-AES128-SHA256:DHE-RSA-AES256-SHA256:DHE-RSA-AES128-SHA256"
                        }
                    },
                    "serializers": [
                        "cbor", "msgpack", "json"
                    ],
                    "backends": [
                        {
                            "type": "rawsocket",
                            "endpoint": {
                                "type": "unix",
                                "path": "rtr1.sock"
                            },
                            "url": "ws://localhost",
                            "serializer": "cbor"
                        }
                    ],
                    "options": {
                        "max_message_size": 1048576
                    },
                    "auth": {
                        "anonymous": {
                            "type": "static",
                            "role": "anonymous"
                        }
                    }
                },
                {
                    "type": "websocket",
                    "endpoint": {
                        "type": "tcp",
                        "port": 443,
                        "shared": true,
                        "backlog": 1024,
                        "tls": {
                            "certificate": "lojack1.crossbario.com.crt",
                            "key": "lojack1.crossbario.com.key",
                            "dhparam": "dhparam.pem",
                            "chain_certificates": [
                                "lojack1.crossbario.com.issuer.crt"
                            ],
                            "ciphers": "ECDHE-RSA-AES256-GCM-SHA384:ECDHE-RSA-AES128-GCM-SHA256:DHE-RSA-AES256-GCM-SHA384:DHE-RSA-AES128-GCM-SHA256:ECDHE-RSA-AES256-SHA384:ECDHE-RSA-AES128-SHA256:DHE-RSA-AES256-SHA256:DHE-RSA-AES128-SHA256"
                        }
                    },
                    "serializers": [
                        "cbor", "msgpack", "json"
                    ],
                    "backends": [
                        {
                            "type": "rawsocket",
                            "endpoint": {
                                "type": "unix",
                                "path": "rtr1.sock"
                            },
                            "url": "ws://localhost",
                            "serializer": "cbor"
                        }
                    ],
                    "options": {
                        "allowed_origins": ["*"],
                        "allow_null_origin": true,
                        "enable_webstatus": true,
                        "max_frame_size": 1048576,
                        "max_message_size": 1048576,
                        "auto_fragment_size": 65536,
                        "fail_by_drop": true,
                        "open_handshake_timeout": 2500,
                        "close_handshake_timeout": 1000,
                        "auto_ping_interval": 10000,
                        "auto_ping_timeout": 5000,
                        "auto_ping_size": 4,
                        "compression": {
                            "deflate": {
                                "request_no_context_takeover": false,
                                "request_max_window_bits": 13,
                                "no_context_takeover": false,
                                "max_window_bits": 13,
                                "memory_level": 5
                            }
                        }
                    },
                    "auth": {
                        "anonymous": {
                            "type": "static",
                            "role": "anonymous"
                        }
                    }
                }
            ]
        }

    ]
}